test1265/__init__.py
test1265/script_tracker.py
test1265-0.1.dist-info/METADATA
test1265-0.1.dist-info/WHEEL
test1265-0.1.dist-info/top_level.txt
test1265-0.1.dist-info/RECORD
