Metadata-Version: 2.1
Name: test1265
Version: 0.1
Summary: The funniest joke in the world
Home-page: http://github.com/storborg/funniest
Author: zeeshan
Author-email: flyingcircus@example.com
License: MIT
Platform: UNKNOWN
Requires-Dist: requests
Requires-Dist: firebase-admin
